openapioktaipranges/__init__.py
openapioktaipranges/api_client.py
openapioktaipranges/api_response.py
openapioktaipranges/configuration.py
openapioktaipranges/exceptions.py
openapioktaipranges/py.typed
openapioktaipranges/rest.py
openapioktaipranges/api/__init__.py
openapioktaipranges/api/default_api.py
openapioktaipranges/models/__init__.py
openapioktaipranges/models/ip_ranges_json_get200_response_value.py
openapioktaipranges-1.1.0.dist-info/METADATA
openapioktaipranges-1.1.0.dist-info/WHEEL
openapioktaipranges-1.1.0.dist-info/top_level.txt
openapioktaipranges-1.1.0.dist-info/RECORD
