Metadata-Version: 2.4
Name: openapioktaipranges
Version: 1.1.0
Summary: OpenAPI Okta IP Ranges
Home-page: https://github.com/oapicf/openapi-okta-ip-ranges
Author: OpenAPI Okta IP Ranges
Author-email: OpenAPI Okta IP Ranges <blah+oapicf@cliffano.com>
License: MPL-2.0
Project-URL: Repository, https://github.com/oapicf/openapi-okta-ip-ranges
Keywords: OpenAPI,OpenAPI-Generator,OpenAPI Okta IP Ranges
Requires-Python: >=3.9
Requires-Dist: urllib3<3.0.0,>=2.1.0
Requires-Dist: python-dateutil>=2.8.2
Requires-Dist: pydantic>=2
Requires-Dist: typing-extensions>=4.7.1
Dynamic: author
Dynamic: home-page
